modbus4mqtt/__init__.py
modbus4mqtt/genconfig.py
modbus4mqtt/modbus4mqtt.py
modbus4mqtt/modbus_interface.py
modbus4mqtt/version.py
tests/__init__.py
tests/test_modbus.py
tests/test_mqtt.py
modbus4mqtt-0.7.0.dist-info/LICENSE
modbus4mqtt-0.7.0.dist-info/METADATA
modbus4mqtt-0.7.0.dist-info/WHEEL
modbus4mqtt-0.7.0.dist-info/entry_points.txt
modbus4mqtt-0.7.0.dist-info/top_level.txt
modbus4mqtt-0.7.0.dist-info/RECORD
