Metadata-Version: 2.1
Name: modbus4mqtt
Version: 0.7.0
Summary: A YAML-defined bidirectional Modbus to MQTT interface
Home-page: https://github.com/tjhowse/modbus4mqtt
Author: Travis Howse
Author-email: tjhowse@gmail.com
License: UNKNOWN
Platform: UNKNOWN
Classifier: Programming Language :: Python :: 3
Classifier: License :: OSI Approved :: GNU General Public License v3 (GPLv3)
Classifier: Operating System :: OS Independent
Requires-Python: >=3.5.0
Requires-Dist: ruamel.yaml (>=0.16.12)
Requires-Dist: paho-mqtt (<2,>=1.5.0)
Requires-Dist: pymodbus (<3.0.0,>=2.3.0)
Requires-Dist: click (>=6.7)
Requires-Dist: SungrowModbusTcpClient (>=0.1.6)
